eventit_py/__init__.py
eventit_py/base_logger.py
eventit_py/event_logger.py
eventit_py/logging_backends.py
eventit_py/pydantic_events.py
eventit_py-0.1.1.dist-info/LICENSE
eventit_py-0.1.1.dist-info/METADATA
eventit_py-0.1.1.dist-info/WHEEL
eventit_py-0.1.1.dist-info/RECORD
