Metadata-Version: 2.1
Name: eventit-py
Version: 0.1.1
Summary: 
Home-page: https://github.com/alexdlukens/eventit-py
License: GPL-3.0-or-later
Author: Alexander Lukens
Author-email: alexdlukens@gmail.com
Requires-Python: >=3.10,<4.0
Classifier: Development Status :: 3 - Alpha
Classifier: Intended Audience :: Developers
Classifier: License :: OSI Approved :: GNU General Public License v3 (GPLv3)
Classifier: License :: OSI Approved :: GNU General Public License v3 or later (GPLv3+)
Classifier: Operating System :: OS Independent
Classifier: Programming Language :: Python :: 3
Classifier: Programming Language :: Python :: 3.10
Classifier: Programming Language :: Python :: 3.11
Classifier: Programming Language :: Python :: 3.12
Classifier: Topic :: Software Development :: Libraries :: Python Modules
Requires-Dist: pydantic (>=2.6.1,<3.0.0)
Requires-Dist: pymongo (>=4.6.1,<5.0.0)
Project-URL: Documentation, https://alexdlukens.github.io/eventit-py/#
Project-URL: Repository, https://github.com/alexdlukens/eventit-py
